{
  "cardNumber": 115,
  "group": "collectorsalbum:nature",
  "itemMap": {
    "collectorsalbum:common_golden_carrot_card": {
      "rarity": "COMMON",
      "extraPoints": 0
    },
    "collectorsalbum:uncommon_golden_carrot_card": {
      "rarity": "UNCOMMON",
      "extraPoints": 0
    },
    "collectorsalbum:rare_golden_carrot_card": {
      "rarity": "RARE",
      "extraPoints": 0
    },
    "collectorsalbum:epic_golden_carrot_card": {
      "rarity": "EPIC",
      "extraPoints": 0
    },
    "collectorsalbum:legendary_golden_carrot_card": {
      "rarity": "LEGENDARY",
      "extraPoints": 0
    },
    "collectorsalbum:mythical_golden_carrot_card": {
      "rarity": "MYTHICAL",
      "extraPoints": 0
    }
  }
}